[
  {
    "source_system": "csod-house-cao",
    "source_organization": "Office of the CAO",
    "source_job_id": "4256",
    "source_url": "https://house.csodfed.com/ux/ats/careersite/1/home/requisition/4256?c=house",
    "title": "Benefits Specialist",
    "description_text": "Benefits Specialist\n\nSalary Range:\u00a0 73,712.00 - 84,271.00\n\nClosing Date:\u00a0\u00a03/23/2026\n\nJob Summary:\u00a0\n\n\u00a0\n\nThe Office of the Chief Administrative Officer (CAO) provides operations support services and business solutions to the community of 10,000 House Members, Officers and staff. The CAO organization comprises more than 700 technical and administrative staff working in a variety of areas, including information technology, finance, budget management, human resources, payroll, child care, food and vending, procurement, logistics and administrative counsel.\u00a0\n\n\u00a0\n\nThe purpose of the Office of Finance under the Chief Administrative Officer (CAO) at the U. S. House of Representatives is to provide financial management services to Leadership, Members, Committees, Officers, and Support Service offices of the House. The Office Payroll and Benefits within the Office of Finance is responsible for the administration of staff payroll and benefits in accordance with applicable laws, rules, and regulations. This position serves as a Benefits Specialist within the Office of Payroll and Benefits.\u00a0\n\n\u00a0\n\nKey responsibilities include providing information to current and former House employees regarding Federal and House specific benefits, and how to enroll in them.\u00a0 To do this, the Benefits Specialist must maintain proficient knowledge in one or more specialty areas (e.g., Federal health, dental and vision insurance, flexible spending accounts, Thrift Savings Plan, payroll and benefit records, and/or retirement), distribute effective communications and, assist with providing training and briefings to the House community.\u00a0 Methods of contact with customers is by email, telephone and in-person, each of which requires excellent communication skills.\u00a0\n\n\u00a0\n\nGrade level at time of the candidates initial appointment is determined by past experience.\u00a0\u00a0\u00a0\n\nThis position has access to Personally Identifiable Information (PII).\u00a0\n\nThe position does not have day-to-day supervisory/managerial responsibilities.\u00a0\n\n\u00a0\n\nPrimary Duties/Responsibilities:\u00a0\n\n\u00a0\n\nProvides advisory services to management and current and former House employees on a variety of benefits and entitlement programs and services, including the Thrift Savings Plan (TSP), Federal Employees Health Benefits (FEHB), Affordable Care Act health coverage, Federal Employees Group Life Insurance (FEGLI), retirement programs/options, beneficiary information, debt collection, creditable civilian/military service.\u00a0\u00a0\nDistributes communications, such as monthly newsletters and information about initial benefit enrollment, to assigned customers.\u00a0\u00a0\nAssists with training and briefings to the House community on a regular basis.\u00a0\nServes as a benefits consultant, participating in the development and accomplishment of plans and special projects related to the technical support of the Department and services rendered to customers.\u00a0\u00a0\u00a0\u00a0\nMaintains proficient knowledge in one or more Department specialty areas (e.g., TSP, Payroll and Benefits Records, Retirement, etc.). Answers general inquiries and questions about the interrelationship between different areas.\u00a0\u00a0\nCounsels and advises employees regarding the immediate and long-term advantages of participating in the Thrift Savings Plan (TSP), procedures for enrolling, and procedures for changing or canceling TSP participation. (Provides general information and guidance to assist employees with retirement.)\u00a0\u00a0\nAdvises survivors of deceased employees with general information on their benefits.\u00a0\nResearches, interprets, and accurately applies relevant laws, rules, regulations, polices, processes, and procedures.\u00a0\u00a0\u00a0\u00a0\u00a0\nAnalyzes data using appropriate methods and tools.\u00a0\nUses financial systems/software to research and troubleshoot issues.\u00a0\u00a0\u00a0\nPerforms most or all the specialty services described below:\u00a0\u00a0\nProcesses applications and makes adjustments to health insurance enrollment, which includes determining eligibility and the needed documentation.\u00a0\u00a0\nReviews TSP enrollment forms for accuracy.\u00a0\u00a0\nCalculates payroll adjustments related to the TSP, health, or life insurance, when required.\u00a0\nCoordinates benefits for concurrent employees with other federal agencies to include issuing correspondence and adjusting necessary benefits.\u00a0\nCalculates Service Computation Dates (SCDs) for newly appointed employees with prior federal service.\u00a0Verifies prior federal service and benefits for appointed employees.\u00a0\u00a0\nProvides employees with information about the eligibility for retirement.\u00a0\nReviews student loan program agreements, reviews validity of submitted loan service provider information, and validates data entry.\u00a0\u00a0\nPrepares reports and statistical compilations and researches and answers correspondence related to areas of expertise.\u00a0\nInstructs, trains, and mentors peers as needed.\u00a0\u00a0\nUtilizes Adobe and Microsoft products a proficient manner.\u00a0 The latter includes, Outlook, Teams, Word, Excel and PowerPoint.\u00a0\u00a0\u00a0\nPerforms other official duties as assigned.\n\n\n\nMinimum Experience and/or Education Requirements:\n\n\u00a0\u00a0\n\nHigh school diploma or G.E.D. plus two or more years related experience (experience with federal employee benefits and compensation programs - particularly Legislative Branch programs, desirable) or equivalent combination of education and/or experience required.\u00a0\u00a0\u00a0\n\n\u00a0\n\nPreferred:\n\n\u00a0\u00a0\n\nCompletion of specialized training in relevant human resources subject areas, (e.g. federal benefits) which may be completed as part of college course work, independent courses or comparable on-the-job-training.\u00a0\nBachelor\u2019s degree.\u00a0\nSHRM, APA or OPM certification/accreditations.\n\n\u00a0\n\nContinued employment is contingent upon satisfactorily completing a criminal history records check (or other applicable security clearance) and a pre-employment drug-test (pre-identified position only).\u00a0\n\n\n",
    "location_text": "WASHINGTON, DC, United States",
    "employment_type": null,
    "salary_min": 73712.0,
    "salary_max": 84271.0,
    "salary_period": "yearly",
    "posted_at": null,
    "closing_at": "2026-03-23T00:00:00"
  },
  {
    "source_system": "csod-house-cao",
    "source_organization": "Office of the CAO",
    "source_job_id": "4238",
    "source_url": "https://house.csodfed.com/ux/ats/careersite/1/home/requisition/4238?c=house",
    "title": "Communications Director",
    "description_text": "Communications Director\n\nSalary Range:\u00a0 122,345.00 - 141,786.00\n\nClosing Date:\u00a0\u00a03/20/2026\n\nJob Summary:\n\nThe Office of the Chief Administrative Officer (CAO) provides operations support services and business solutions to the community of 10,000 House Members, Officers, and staff. The CAO organization comprises more than 800 technical and administrative staff working in a variety of areas, including information technology, finance, budget management, human resources, payroll, childcare, food and vending, procurement, logistics and administrative counsel.\n\nThis position is located in the Communications and Marketing Department, Immediate Office, Office of the Chief Administrative Officer (CAO), U.S. House of Representatives (House). Whether it's creating a campaign to advertise the popular CAO House Staff Conferences, assisting a CAO department on messaging around their newest service for the House community, or guiding the editorial team through the Congressional Transition, the Communications Director will play a key role on the Communications and Marketing team and CAO at-large.\n\nWorking alongside the Creative Director, the Communications Director will keep a pulse on what the House campus is buzzing about, the latest trends, and creative new opportunities to reach House staff. The best fit for this role is someone who can work under tight deadlines while handling multiple projects, knows the power of data-centered campaigns, and wants to lead a highly creative editorial team.\n\nKey responsibilities include supervising the editorial team; working closely with the Chief of Communications to create and execute high-priority communication plans for specific projects and customers; collaborating with the Creative Director to ensure alignment between the communications team and the design team.\n\nThe position has day-to-day supervisory/managerial responsibilities.\n\nPrimary Duties/Responsibilities:\n\n\u00b7\u00a0\u00a0\u00a0\u00a0\u00a0\u00a0 Manages the communications team and monitor deadlines for all communications projects. This includes but is not limited to copy editing and strategic planning.\n\n\u00b7\u00a0\u00a0\u00a0\u00a0\u00a0\u00a0 Coordinates with the Creative Director to ensure the communications and design team members are aligned on projects, deadlines, and other important information that could impact the deliverable(s).\n\n\u00b7\u00a0\u00a0\u00a0\u00a0\u00a0\u00a0 Collaborates with leaders across the CAO to brand and market products and services; serves as a partner with CAO business units as they plan, develop, and implement new products and services for the House community.\n\n\u00b7\u00a0\u00a0\u00a0\u00a0\u00a0\u00a0 Collaborates with the Communications Chief and Creative Director to identify opportunities for new communications initiatives.\u00a0\n\n\u00b7\u00a0\u00a0\u00a0\u00a0\u00a0\u00a0 Collaborates with the editorial team to provide consultative services to CAO departments about their communications projects.\n\n\u00b7\u00a0\u00a0\u00a0\u00a0\u00a0\u00a0 Develops, composes, and executes comprehensive communications plans for CAO services and initiatives targeted at increasing awareness and usage by Members, Committees, and Leadership.\n\n\u00b7\u00a0\u00a0\u00a0\u00a0\u00a0\u00a0 Assists in the writing and copy editing of the CAO\u2019s Semiannual Report.\n\n\u00b7\u00a0\u00a0\u00a0\u00a0\u00a0\u00a0 Tracks and utilizes analytics for CAO communications.\n\n\u00b7\u00a0\u00a0\u00a0\u00a0\u00a0\u00a0 Develops performance plans and evaluates employee performance.\n\n\u00b7\u00a0\u00a0\u00a0\u00a0\u00a0\u00a0 Performs other official duties and special projects as assigned.\n\n\n\n\nQualifications:\n\nApplicants must submit a resume and writing sample (e.g., a press release or blog post), and meet the following requirements:\n\nMinimum:\n\n\u00b7\u00a0\u00a0\u00a0\u00a0\u00a0\u00a0 Bachelor\u2019s degree in Business, Communications, Advertising, Marketing; OR an equivalent combination of education and experience.\n\n\u00b7\u00a0\u00a0\u00a0\u00a0\u00a0\u00a0 8-10 years of experience in marketing/communications with an advertising agency, on Capitol Hill, or within a marketing and communications department.\n\n\u00b7\u00a0\u00a0\u00a0\u00a0\u00a0\u00a0 3-5 years of progressive management or leadership experience.\n\n\u00b7\u00a0\u00a0\u00a0\u00a0\u00a0\u00a0 Experience with marketing campaign management.\n\n\u00b7\u00a0\u00a0\u00a0\u00a0\u00a0\u00a0 Strong understanding of branding strategies.\n\n\u00b7\u00a0\u00a0\u00a0\u00a0\u00a0\u00a0 Ability to understand analytics and collect data to drive communications decisions.\n\n\u00b7\u00a0\u00a0\u00a0\u00a0\u00a0\u00a0 Knowledge of project management tools (e.g.: ClickUp, Monday, Trello, etc.)\n\n\u00b7\u00a0\u00a0\u00a0\u00a0\u00a0\u00a0 All employees within CAO are expected to demonstrate the following general competencies: Accountability, Adaptability, Collaboration, Communication, Customer Orientation, Knowledge of Relevant Policies, Procedures, and Processes, Priority Management, and Problem Resolution.\n\n*Continued employment is contingent upon satisfactorily completing a criminal history records check (or other applicable security clearance) and a pre-employment drug-test (pre-identified position only).",
    "location_text": "WASHINGTON, DC, United States",
    "employment_type": null,
    "salary_min": 122345.0,
    "salary_max": 141786.0,
    "salary_period": "yearly",
    "posted_at": null,
    "closing_at": "2026-03-20T00:00:00"
  },
  {
    "source_system": "csod-house-cao",
    "source_organization": "Office of the CAO",
    "source_job_id": "4236",
    "source_url": "https://house.csodfed.com/ux/ats/careersite/1/home/requisition/4236?c=house",
    "title": "Cloud Automation Engineer",
    "description_text": "Cloud Automation Engineer\n\nSalary Range:\u00a0 155,689.00 - 163,349.00\n\nClosing Date:\u00a0\u00a03/15/2026\n\nJob Summary:\u00a0\n\n\u00a0\n\nThe Office of the Chief Administrative Officer (CAO) provides operations support services and business solutions to the community of 10,000 House Members, Officers and staff. The CAO organization comprises more than 650 technical and administrative staff working in a variety of areas, including information technology, finance, budget management, human resources, payroll, childcare, food and vending, procurement, logistics and administrative counsel.\u00a0\n\n\u00a0\u00a0\n\nThe candidate must have a work experience in Data Storage Systems Administration, Enterprise Server operations, Data Center Operations, BC/DR, and Enterprise Data Protection and recovery s including Backups, Snapshots and Data Replication.\u00a0 Duties include, but are not limited to, managing day-to-day Operations of the SAN/NAS/Object storage environments, new technology research/integration and heavy technical support. This position requires the candidate to be proficient in Storage provisioning and connectivity to a variety of systems (Physical and Virtual Server and OS platforms VMware, Unix, Windows & Kubernetes container environments).\u00a0\n\n\u00a0\u00a0\n\nCandidates are required to work a diversified schedule and participate in 24x7 on-call support.\u00a0\u00a0\n\n\u00a0\u00a0\n\nThis position has access to Personally Identifiable Information (PII).\u00a0\n\n\u00a0\n\nThe position does not have day-to-day supervisory/managerial responsibilities.\u00a0\n\n\u00a0\n\nPrimary Duties/Responsibilities:\u00a0\n\n\n\n\nDeliver exceptional services to House via a stable, reliable and secure environment. Respond, diagnose and remediate issues affecting production availability in a dynamic environment\u00a0\u00a0\nSupport day-to-day operations.\u00a0\u00a0\nImplement, configure and maintain SAN, NAS Storage and Cloud solutions in a Virtual and Physical servers\u2019 environment; Conduct proof of concepts, Maintain environment with current releases of firmware and operating systems up to date\u00a0\nInstalls, maintains, configures, monitors, and supports all hardware systems and software components on the applicable platforms.\u00a0\u00a0\nGenerate and compile Performance and Capacity reports and metrics.\u00a0\u00a0\nMust demonstrate willingness and aptitude to continually learn and adapt to new technologies.\u00a0\nPosition requires the ability to work shifts to provide technical support 24 hours a day, 7 days a week, participate in an On-Call rotation and be available OnDemand to address technical problems and support after-hours and weekend maintenance activities on a needed basis. This position requires occasional travel to multiple locations, as assigned.\u00a0\nDemonstrate effective ticket queue etiquette by consistently resolving tickets in a timely manner and communicate promptly using email. Maintain accurate and precise ticket notes within each assigned service ticket that effectively relay what occurred while supporting the ticket and the outcome and/or path forward.\u00a0\nTroubleshooting and analytical skills; ability to anticipate and resolve technical problems in a Storage and Server environment.\u00a0\nCollaborate and Interact with other internal HIR Teams and external vendors as assigned. Act as a facilitator for team meetings on a rotating basis, as assigned.\u00a0\nPerform training sessions that will be resourceful and provide additional knowledge on a variety of technical topics for peers.\u00a0\nDevelop, maintain and assist in writing, structuring, and organizing technical documentation and standard operating procedures\u00a0\nProvides technical advice to management regarding future and directions as server and network technologies continue to evolve\u00a0\nActs as an internal consultant providing technical guidance on the most complex projects; regularly provides technical leadership to colleagues, assisting them with successfully completing assigned projects.\u00a0\nPlans and recommendations for changes to the configuration and capacity/performance of the operating system.\u00a0\nPrepares long and short-range plans for systems maintenance, production activities, and for necessary support resources.\u00a0\nEnsures computer systems security issues are addressed effectively in the House environment for all components of the platform operating system environment (e.g., network, desktop, Internet).\u00a0\u00a0\nDemonstrates willingness and cooperation in participating in matrix managed projects.\u00a0\nMaintains professional relationships with customers, management, colleagues, and vendors while delivers high-quality customer service.\u00a0\nProvides input to management, as requested, on project team performance for Individual Performance Plans and employee performance evaluations.\u00a0\u00a0\nPerforms other official duties and projects assigned.\u00a0\n\n\n\n\nMinimum Requirements:\u00a0\n\n\n\n\nBachelor\u2019s degree in computer science/engineering, Information Systems, Information Technology, degree with 5+ years of relevant storage experience as an Information Technology professional in an organization.\u00a0\n\n\u00a0\u00a0\u00a0\n\nKnowledge, Skill, and Ability (KSA) and Competency Requirements:\u00a0\u00a0\n\n\u00a0\u00a0\n\nPossess 5+ years of experience in Storage administration of SAN, NAS, Storage and Data Protection technologies, Architectures, Design, Administration and Support of Storage systems in a data center environment.\u00a0\nKnowledge of Data and Storage system Security, Web Applications, Databases, VMware, Windows, UNIX servers and Kubernetes Containers.\u00a0\u00a0\nKnowledge of Local Area Networks, Wide Area networks, Operating systems, Storage Area Network (SAN), Network Attached Storage (NAS) and backup solutions.\u00a0\nKnowledge of Network File share Administration CIFS and NFS\u00a0\u00a0\nKnowledge in Cloud Storage connectivity, Tiering to Cloud\u00a0\u00a0\nExpertise in Enterprise level NetApp, Pure Storage systems/arrays and Cisco MDS SAN switches is preferred.\u00a0\nKnowledge of Microsoft File NAS. Administration of File share and Windows NTFS Folder and File permissions, access, ACLs in an Active Directory environment\u00a0\nAbility to develop and deploy customized solutions\u00a0\nCertification in Storage Systems is preferred. Possessing certification in other storage and cloud technologies is a plus\u00a0\nAll employees within CAO are expected to demonstrate the following general competencies: Accountability, Adaptability, Collaboration, Communication, Customer Orientation, Knowledge of Relevant Policies, Procedures, and Processes, Priority Management, and Problem Resolution.\u00a0\nAbility to communicate effectively, both orally and in writing, with peers, senior staff, information systems professionals, and the user community\u00a0\n\u00a0A strong desire to learn and expand on existing knowledge is a requirement. Ability to grasp fundamentals of new technologies quickly and employ in organization.\u00a0\u00a0\nKnowledge on Automation of Storage administration tasks and jobs using tools\u00a0\nTroubleshooting and analytical skills; ability to anticipate and resolve technical problems\u00a0\nAbility to develop solutions to complex technical problems.\u00a0\u00a0\nKnowledge of platform specific operating systems and associated products.\u00a0\u00a0\nKnowledge of all phases of projects, systems analysis and administration.\u00a0\n\n\u00a0\n\nSecurity Requirements:\u00a0\n\n\u00a0\n\nThis position requires unescorted access to secure offsite locations which require an identification badge. In order to be approved for the applicable badge, you must be a U.S. citizen.\u00a0\n\n\u00a0\n\nThis position requires that the applicant obtain and maintain an applicable U.S. Government security clearance, which requires U.S. citizenship. We will not submit your application for a clearance unless you are a U.S. citizen.\u00a0\n\n\u00a0\u00a0\n\n**Continued employment is contingent upon satisfactorily completing a criminal history records check (or other applicable security clearance, a pre-employment drug-test) and a probationary period of 2 years.\n\n\u00a0\u00a0\n\n\n",
    "location_text": "WASHINGTON, DC, United States",
    "employment_type": null,
    "salary_min": 155689.0,
    "salary_max": 163349.0,
    "salary_period": "yearly",
    "posted_at": null,
    "closing_at": "2026-03-15T00:00:00"
  },
  {
    "source_system": "csod-house-cao",
    "source_organization": "Office of the CAO",
    "source_job_id": "4221",
    "source_url": "https://house.csodfed.com/ux/ats/careersite/1/home/requisition/4221?c=house",
    "title": "Senior Project Designer",
    "description_text": "Senior Project Designer\n\nSalary Range:\u00a0 84,271.00 - 92,783.00\n\nClosing Date:\u00a0\u00a03/12/2026\n\nJob Summary:\n\nThe Office of the Chief Administrative Officer (CAO) provides operations support services and business solutions to the community of 10,000 House Members, Officers and staff. The CAO organization comprises more than 800 technical and administrative staff working in a variety of areas, including information technology, finance, budget management, human resources, payroll, childcare, food and vending, procurement, logistics and administrative counsel.\n\nThe position is with House Interior Design, Office of Logistics & Support (L&S), Office of the Chief Administrative Officer (CAO), U.S. House of Representatives (House). The purpose of the Office of L&S is to provide important logistical services to the entire House community, including building, repairing, moving, setting up, and breaking down furniture; facilitating office moves; and managing all accountable equipment assets within the House. The purpose of House Interior Design is to serve as the main point of contact for Leadership, Committee and Member office design, specializing in design consultation services using Antique and Unique, Core and Modular furniture from the House inventory as well as special order furnishings to support Finish Schedule projects. This position serves as a Senior Project Designer.\n\nKey responsibilities include planning, managing, and monitoring House Interior Design projects; tracking project progress; coordinating with other personnel both internal and external in support of project progress; creating accurate furniture plans, 3D renderings and visually effective presentations; providing excellent and consistent customer service; serve as an expert in furniture provided by the House, and as a mentor and trainer to colleagues.\u00a0\n\nThe position does not have day-to-day supervisory/managerial responsibilities.\n\nPrimary Duties/Responsibilities:\n\nProvides interior design services to Members, Committees, and House support offices; applies skills and experience to plan, manage, and monitor House related furniture projects, office consultations, and renovations.\nAssists with multiple projects across varying types of design (A&U, Finish Schedule and/or Modular) and can shift priorities quickly as needed to support MCL requests.\nHelps manage incoming requests. Answers routine inquiries and ensures that adequate office coverage is maintained during official business hours. Delivers excellent customer service; ensures the availability of support services and provides accurate and timely information.\nEstablishes and maintains good working relationships with key stakeholders and customers; establishes credibility in all interactions. Coordinates with other individuals/teams within the Office of Logistics and Support, CAO and external agencies (AOC, USCP, Clerk, and HSAA) in support of project completion.\nLeads by overseeing and monitoring projects that include floor plans, carpet and drape selections; provides expert assistance and adept guidance in administering, managing, and evaluating these projects. Demonstrates excellent project management skills to include proactive customer engagement and professional written and verbal communication to facilitate project coordination, customer satisfaction, problem resolution, and schedule tracking.\nUses architectural plans to complete office designs; provides guidance and insight on floor plans, item placement, and the usage of various materials; applies industry standards for product specification appropriate for contract/government interiors; applies design recommendation in accordance with the Americans with Disabilities Act (ADA).\nCreates realistic 3D renderings incorporating accurate room details using proposed patterns, colors, and finishes.\nEvaluates and assesses House furniture assets for condition and required shop-work; collaborates with shops to write corresponding tickets to perform refurbishment and delivery.\nApplies knowledge of high quality, American-made commercial, residential and/or hospitality sources for furniture, carpet, and drapery applicable to finish schedule or other special projects.\nConducts vendor outreach and coordination for price quotes, material reserves, and site visits as required to inspect furniture for quality and order accuracy.\nReviews vendor quotes/purchase orders to ensure accuracy and compliance; takes corrective action to rectify problems or prepares recommendations, as needed.\nAssist with the curation and evaluation of product lines based on quality, durability, popularity and ease of in-house maintenance and repair.\nDistributes various communications to customers, stakeholders, and staff regarding deadlines, policies, business process changes, and other department specific guidelines related to design services.\nPresents results, status reports, and analyses to management, including metric reports based on project schedule.\nUnderstands and adheres to policies, procedures, and processes; aids others as needed.\nDemonstrates knowledge of the formal and informal structures and workflow within the organization.\nDemonstrates an understanding of the legislative environment and the operational practices of the House.\nServes as the Contracting Officer Representative (COR) for design resource contracts.\nAssists in planning and executing activities related to the bi-annual Congressional transition and determining resource needs.\nMaintains and manages records as appropriate and in accordance with relevant policies and procedures.\nRecommends improvements to policies, procedures, and processes; assists in implementing improvements to enhance efficiency and effectiveness.\nPromotes an environment of coaching, teamwork, creative thinking, and support.\nPerforms other official duties and special projects as assigned.\n\nMinimum Qualifications:\n\nBachelor\u2019s degree in Interior Design, Interior Architecture or related field.\u00a0\nMinimum of three (3) years of relevant experience.\nSoftware competency in AutoCAD (or similar CAD software for space planning) and SketchUp, Lumion, CET designer (or similar 3D rendering software).\nDemonstrated competency in written and oral presentation skills and supporting software such as Microsoft Office, Adobe Creative suite, etc.\nProficient in project management skills, especially workload prioritization and customer service.\nKnowledge of SharePoint, ClickUp, and Microsoft Project is preferred.\nPortfolio demonstrating interior design experience including furnishing sourcing and 3D rendering skills.\u00a0\nWork experience within the legislative branch and the House environment (e.g., Capitol Hill, House customers).\nKnowledge of the design operations and services offered by the Office of Logistics and Support.\u00a0\nAdept in communicating with high-level stakeholders, customers, and leadership to discuss office designs and relocation efforts.\u00a0\nAbility to manage highly confidential and sensitive information appropriately.\n\nPreferred Qualifications\u00a0\n\nCertifications in NCIDQ or Interior Design\nASID or IIDA membership\nKnowledge of project management software, (e.g. sharepoint, click up)\n\nContinued employment is contingent upon satisfactorily completing a criminal history records check (or other applicable security clearance) and a pre-employment drug-test (pre-identified position only).\n\n\n\n\n",
    "location_text": "WASHINGTON, DC, United States",
    "employment_type": null,
    "salary_min": 84271.0,
    "salary_max": 92783.0,
    "salary_period": "yearly",
    "posted_at": null,
    "closing_at": "2026-03-12T00:00:00"
  },
  {
    "source_system": "csod-house-cao",
    "source_organization": "Office of the CAO",
    "source_job_id": "4220",
    "source_url": "https://house.csodfed.com/ux/ats/careersite/1/home/requisition/4220?c=house",
    "title": "Senior Systems Engineer (Linux Systems Admin)",
    "description_text": "Senior Systems Engineer (Linux Systems Admin)\n\nSalary Range:\u00a0 122,345.00 - 154,171.00\n\nClosing Date:\u00a0\u00a03/17/2026\n\nJob Summary:\n\nThe Office of the Chief Administrative Officer (CAO) provides operations support services and business solutions to the community of 10,000 House Members, Officers and staff. The CAO organization comprises more than 800 technical and administrative staff working in a variety of areas, including information technology, finance, budget management, human resources, payroll, child care, food and vending, procurement, logistics and administrative counsel.\n\nWe are looking for a Linux System Administrator to join our dynamic team of system engineers who are responsible for designing, implementing, and monitoring our Linux infrastructure. This position is located in the Enterprise Infrastructure Directorate, House Information Resources (HIR), Office of the Chief Administrative Officer (CAO), U.S. House of Representatives (House). The Enterprise Infrastructure Directorate provides engineering and technical support in the following areas: Voice Communications, Data Center Operations, Server and Storage Management, and Administrative Support. The teams within this Directorate support the infrastructure (circuits, cabling, servers, data storage, voice systems, and other physical infrastructure) that provides computing and telecommunications services to the House. This position serves as the Senior Systems Engineer.\n\nKey responsibilities include serving as a key technical resource and senior advisor to management on all technical issues related to the sustainment of various server platforms supporting applications of the House; planning, organizing, installing, and monitoring large and complex technical projects; producing technical solutions to complex problems; and providing leadership and technical guidance to colleagues, assisting them with successfully completing assigned projects.\n\n\u00a0The position does not have day-to-day supervisory/managerial responsibilities.\n\nPrimary Duties/Responsibilities:\n\nProactively maintain and develop Linux infrastructure technology to maintain a 24x7x365 uptime service\nEngineer systems administration related solutions for various project and operational needs\nMaintain best practices on managing systems and services across all environments\nEnsures systems follow security guidelines and standards as well as perform and analyze on going security audits\nResearch, diagnose and resolve complex computer system software and hardware issues as they arise\nProactively monitoring system performance and perform capacity planning\nManage, coordinate, and implement software upgrades, patches, errata and hot fixes as needed\nCreate and modify scripts or applications to perform tasks\nProvide input on ways to improve the stability, security, efficiency, and scalability of the server environment\nCollaborate with other teams and team members to develop automation strategies and deployment processes\nParticipate in an On-Call rotation\nPerforms other official duties as assigned.\n\nMinimum Qualifications:\n\nMinimum 5 years of relevant experience with Previous working experience as a Linux Administrator\nBachelor's degree in Computer Science, Information Systems, or similar relevant degree\nIn depth command line knowledge and troubleshooting of Red Hat OS version 8+ operating systems\nExperience with Red Hat Satellite, Red Hat Ansible Automation Platform and Red Hat Open Shift\nFamiliarity with monitoring tools such as Dynatrace, Nagios Core and Nagios Log Monitoring\nAbility to multi-task\nExperienced in writing shell scripts\nStrong problem solving and communication skills\nFamiliarity with IT management concepts of Virtualization, Containerization, Data Storage, SAN & Data Protection within an enterprise operations environment\nSolid knowledge of protocols such as DNS, HTTP, LDAP, SMTP and SNMP\nFamiliarity with container management tools such as Podman\n\nPreferred Qualifications:\n\nCertifications in - Linux, RHCSA, RHCE, Red hat certified Specialist in Containers and Kubernetes or Red Hat Certified Specialist in OpenShift Administration and AWS\n\nSecurity Requirements:\nThis position requires unescorted access to secure offsite locations which require an identification badge. In order to be approved for the applicable badge, you must be a U.S. citizen.\n\nContinued employment is contingent upon satisfactorily completing a criminal history records check (or other applicable security clearance) and a pre-employment drug-test (pre-identified position only).\n\n\n",
    "location_text": "WASHINGTON, DC, United States",
    "employment_type": null,
    "salary_min": 122345.0,
    "salary_max": 154171.0,
    "salary_period": "yearly",
    "posted_at": null,
    "closing_at": "2026-03-17T00:00:00"
  }
]